odoo/addons/pos_product_pricelist_alternative/README.rst
odoo/addons/pos_product_pricelist_alternative/__init__.py
odoo/addons/pos_product_pricelist_alternative/__manifest__.py
odoo/addons/pos_product_pricelist_alternative/i18n/it.po
odoo/addons/pos_product_pricelist_alternative/i18n/pos_product_pricelist_alternative.pot
odoo/addons/pos_product_pricelist_alternative/models/__init__.py
odoo/addons/pos_product_pricelist_alternative/models/pos_session.py
odoo/addons/pos_product_pricelist_alternative/readme/CONTRIBUTORS.rst
odoo/addons/pos_product_pricelist_alternative/readme/DESCRIPTION.rst
odoo/addons/pos_product_pricelist_alternative/static/description/icon.png
odoo/addons/pos_product_pricelist_alternative/static/description/index.html
odoo/addons/pos_product_pricelist_alternative/static/src/models.js
odoo_addon_pos_product_pricelist_alternative-16.0.1.0.0.4.dist-info/METADATA
odoo_addon_pos_product_pricelist_alternative-16.0.1.0.0.4.dist-info/WHEEL
odoo_addon_pos_product_pricelist_alternative-16.0.1.0.0.4.dist-info/top_level.txt
odoo_addon_pos_product_pricelist_alternative-16.0.1.0.0.4.dist-info/RECORD
