Metadata-Version: 2.1
Name: odoo-addon-pos_product_pricelist_alternative
Version: 16.0.1.0.0.4
Summary: Calculate POS product price based on alternative pricelists
Home-page: https://github.com/OCA/pos
Author: Camptocamp, Odoo Community Association (OCA)
Author-email: support@odoo-community.org
License: AGPL-3
Classifier: Programming Language :: Python
Classifier: Framework :: Odoo
Classifier: Framework :: Odoo :: 16.0
Classifier: License :: OSI Approved :: GNU Affero General Public License v3
Requires-Python: >=3.10
Requires-Dist: odoo-addon-product-pricelist-alternative<16.1dev,>=16.0dev
Requires-Dist: odoo<16.1dev,>=16.0a
